pytransport/Convert.py
pytransport/Data.py
pytransport/Reader.py
pytransport/_General.py
pytransport/__init__.py
pytransport/_version.py
pytransport/Compare/_TransportTransportComparison.py
pytransport/Compare/__init__.py
pytransport-2.0.2.dist-info/COPYING.txt
pytransport-2.0.2.dist-info/LICENSE.txt
pytransport-2.0.2.dist-info/METADATA
pytransport-2.0.2.dist-info/WHEEL
pytransport-2.0.2.dist-info/top_level.txt
pytransport-2.0.2.dist-info/RECORD
