Metadata-Version: 2.1
Name: pytransport
Version: 2.0.2
Summary: Convert TRANSPORT models and load TRANSPORT output.
Author-email: "JAI@RHUL" <william.shields@rhul.ac.uk>
Maintainer-email: William Shields <william.shields@rhul.ac.uk>
Project-URL: homepage, http://www.pp.rhul.ac.uk/bdsim/pytransport
Project-URL: documentation, http://www.pp.rhul.ac.uk/bdsim/pytransport
Project-URL: repository, https://bitbucket.org/jairhul/pytransport
Classifier: Development Status :: 5 - Production/Stable
Classifier: Intended Audience :: Developers
Classifier: Intended Audience :: Science/Research
Classifier: Operating System :: MacOS
Classifier: Operating System :: POSIX
Classifier: Operating System :: Unix
Classifier: Programming Language :: Python
Classifier: Programming Language :: Python :: 3
Classifier: Programming Language :: Python :: 3 :: Only
Classifier: Topic :: Scientific/Engineering
Classifier: Topic :: Scientific/Engineering :: Physics
Classifier: Topic :: Software Development
Requires-Python: >=3.6
License-File: LICENSE.txt
License-File: COPYING.txt
Requires-Dist: matplotlib >=3.0
Requires-Dist: numpy >=1.14
Requires-Dist: scipy
Requires-Dist: importlib-metadata
Provides-Extra: dev
Requires-Dist: pytest ; extra == 'dev'
Requires-Dist: sphinx ; extra == 'dev'
Requires-Dist: sphinx-rtd-theme ; extra == 'dev'
Provides-Extra: root-numpy
Requires-Dist: root-numpy ; extra == 'root-numpy'
